infilake_openapi_auth/__init__.py
infilake_openapi_auth-1.0.0.dist-info/METADATA
infilake_openapi_auth-1.0.0.dist-info/WHEEL
infilake_openapi_auth-1.0.0.dist-info/RECORD
