Metadata-Version: 2.4
Name: infilake-openapi-auth
Version: 1.0.0
Summary: Infilake OpenAPI Authorization SDK for generating HMAC-SHA256 signed headers
Project-URL: Homepage, https://github.com/infilake/openapi-auth-sdk
Project-URL: Documentation, https://github.com/infilake/openapi-auth-sdk#readme
Project-URL: Repository, https://github.com/infilake/openapi-auth-sdk
License: MIT
Keywords: api,auth,authorization,hmac,infilake,sdk,sha256
Classifier: Development Status :: 5 - Production/Stable
Classifier: Intended Audience :: Developers
Classifier: License :: OSI Approved :: MIT License
Classifier: Operating System :: OS Independent
Classifier: Programming Language :: Python :: 3
Classifier: Programming Language :: Python :: 3.8
Classifier: Programming Language :: Python :: 3.9
Classifier: Programming Language :: Python :: 3.10
Classifier: Programming Language :: Python :: 3.11
Classifier: Programming Language :: Python :: 3.12
Classifier: Topic :: Security :: Cryptography
Classifier: Topic :: Software Development :: Libraries :: Python Modules
Requires-Python: >=3.8
Provides-Extra: dev
Requires-Dist: pytest-cov>=4.0; extra == 'dev'
Requires-Dist: pytest>=7.0; extra == 'dev'
